[["cm"
]


,{"typ":"exrc","form":"drill"
,"inst":["ds","Conjugate","Simple Past - Indicative","ser"]
,"lines":[
  { "x":"                 ","pre":"yo ","a":"fui"}
  ,{"x":"                 ","pre":"tú ","a":"fuiste"}
  ,{"x":"      ","pre":"él/ella/usted ","a":"fue"
  ,		"apre":["él ","ella ","usted "]}
  ,{"x":"           ","pre":"nosotros ","a":"fuimos"}
  ,{"x":"           ","pre":"vosotros ","a":"fuisteis"}
  ,{"x":"","pre":"ellos/ellas/ustedes ","a":"fueron"
  ,		"apre":["ellos ","ellas ","ustedes "]}
]
  ,"voca":{"typ":"synth"
    ,"lng":"es"
    ,"gnd":"r"
  }
}



,{"typ":"exrc","form":"blank"}
,{"typ":"exrc","form":"blank"}
,{"typ":"exrc","form":"blank"}
,{"typ":"exrc","form":"blank"}
,{"typ":"exrc","form":"blank"}



]